{
  "title": "내가 가장 잘하는 건",
  "author": "최형미",
  "illustrator": "전선희",
  "isbn": "9791185721309",
  "readAge": "초등_저학년",
  "publishedYear": 2014,
  "publisher": "황우출판사",
  "classification": "신체운동_건강",
  "paragraphInfoCount": 10,
  "paragraphInfo": [
    {
      "srcTextID": "45075",
      "srcText": "원숭이 임금님의 생일잔치가 열렸어요. 동물들이 돌아가며 자기 재능을 뽐내는 멋진 잔치였어요. 하지만 거북이는 끝내 그 자리에 나타나지 않았어요. \"거북이에게 무슨 일이 있느냐?\" 임금님이 묻자 여우가 그동안의 일을 이야기했어요.",
      "srcPage": 13,
      "srcSentenceEA": 5,
      "srcWordEA": 31
    },
    {
      "srcTextID": "45067",
      "srcText": "\"내가 잘하는 게 뭘까?\" 동물들의 표정이 어두워졌어요. \"그럼 자기가 무얼 잘하는지 생각하고 다시 모일까?\" 거북이의 말에 다들 고개를 끄덕였어요.",
      "srcPage": 5,
      "srcSentenceEA": 4,
      "srcWordEA": 21
    },
    {
      "srcTextID": "45068",
      "srcText": "모두 자기들이 잘하는 것을 찾느라 바빴어요. 룰루랄라 노래도 부르고 지글지글 요리도 하고 쿵작쿵작 디리링 악기를 연주하며 덩실덩실 춤도 추었지요. 자기가 잘하는 것을 얼른 찾으려고요.",
      "srcPage": 6,
      "srcSentenceEA": 3,
      "srcWordEA": 26
    },
    {
      "srcTextID": "45072",
      "srcText": "\"내일 멋진 잔치를 열 수 있겠다!\" 동물들은 다들 기뻐했어요. 그런데 그때 갑자기 거북이가 우울한 표정을 지었어요. \"나는 뭘 잘하지?\"",
      "srcPage": 10,
      "srcSentenceEA": 4,
      "srcWordEA": 21
    },
    {
      "srcTextID": "45066",
      "srcText": "숲 속 동물들이 원숭이 임금님의 생일 준비로 정신없이 바빴어요. 마침 그때 거북이가 한 가지 좋은 생각을 해냈어요. 각자 잘하는 걸 준비해서 멋진 잔치를 열자!",
      "srcPage": 4,
      "srcSentenceEA": 3,
      "srcWordEA": 26
    },
    {
      "srcTextID": "45074",
      "srcText": "거북이는 노래를 불렀어요. 하지만 모두들 귀를 막았어요. 거북이는 뚝딱뚝딱 요리에 도전했어요. 하지만 맛은 별로였어요. 춤도 못 추고, 악기 연주도 할 줄 몰랐어요. \"난 잘하는 게 하나도 없나 봐.\" 거북이는 그만 눈물을 터뜨리고 말았어요.",
      "srcPage": 12,
      "srcSentenceEA": 7,
      "srcWordEA": 38
    },
    {
      "srcTextID": "45071",
      "srcText": "거북이의 칭찬은 계속되었어요. \"코끼리야, 넌 어쩜 그렇게 연주를 잘하니?\" 코끼리는 긴 코를 말아 올리며 좋아했어요. \"다람쥐야, 넌 춤을 정말 잘 추는 것 같아!\" 다람쥐도 도토리를 공중으로 던지며 기뻐했어요. \"칭찬해 줘서 고마워!\"",
      "srcPage": 9,
      "srcSentenceEA": 6,
      "srcWordEA": 33
    },
    {
      "srcTextID": "45076",
      "srcText": "임금님은 당장 거북이를 불러 물어보았어요. \"이 흥겨운 잔치를 생각해 낸 건 누구지?\" \"접니다.\" \"친구들이 잘하는 걸 찾아 준 건 누구지?\" \"접니다.\" \"그런데도 네가 잘하는 게 뭔지 모르겠느냐?\" 거북이는 고개를 갸웃거렸어요. \"넌 새로운 생각도 잘 하고, 관찰력도 뛰어나다!\"",
      "srcPage": 14,
      "srcSentenceEA": 6,
      "srcWordEA": 38
    },
    {
      "srcTextID": "45073",
      "srcText": "\"거북아, 왜 그렇게 표정이 어두워?\" \"난 아무리 생각해도 잘하는 게 없는 것 같아.\" 거북이의 눈에 반짝 눈물이 맺혔어요. 그때 여우가 이렇게 제안했어요. \"거북이가 뭘 잘하는지 함께 찾아보자!\"",
      "srcPage": 11,
      "srcSentenceEA": 5,
      "srcWordEA": 29
    },
    {
      "srcTextID": "45077",
      "srcText": "숲 속 동물들이 다들 고개를 끄덕이며 외쳤어요. \"맞아요! 거북이는 잘하는 게 참 많아요!\" 거북이는 비로소 기쁨의 눈물을 흘렸어요. 자신이 무엇을 잘하는지 이제야 알 것 같았거든요. 거북이는 최고예요!",
      "srcPage": 15,
      "srcSentenceEA": 5,
      "srcWordEA": 31
    }
  ]
}